{
  "createBy": "http://liujiacai.net/gooreplacer/",
  "version": "3.13.0",
  "createAt": "2022/7/15 15:10:52",
  "redirect-rules": [
    {
      "src": "http://10.253.102.69/gw/*",
      "kind": "wildcard",
      "dst": "http://localhost:18080/services/10.253.102.69/gw/",
      "enable": true
    },
    {
      "src": "http://localhost:8000/data/*",
      "kind": "wildcard",
      "dst": "http://localhost:18080/data/",
      "enable": true
    },
    {
      "src": "http://localhost:8000/gws/*",
      "kind": "wildcard",
      "dst": "http://localhost:18080/gws/",
      "enable": true
    },
    {
      "src": "http://localhost:8000/gongwushu/*",
      "kind": "wildcard",
      "dst": "http://localhost:18080/gongwushu/",
      "enable": true
    }
  ],
  "cancel-rules": [],
  "request-headers": [],
  "response-headers": []
}